{
  "artists": [
    {
      "id": "59013a15-d528-44c3-850a-1a2c4ac0d46a",
      "name": "Adrian Clark",
      "sort_name": "Adrian Clark",
      "summary": "Fresh of the release of his Second EP, “These Moments”, and hailing from Albury/Wodonga, this Indie Singer-Songwriter, Adrian Clark, will take you on a journey through heartache and out the other side. A new twist on the old classic, let this one man percussive guitar show, tell you a story about life, music, love and beyond.",
      "image_name": "AdrianClark",
      "website": "https://www.adrianclarkmusic.com.au/",
      "youtube": "https://www.youtube.com/channel/UCFSBkul8fqGNz38clOH4VZw",
      "itunes": "https://music.apple.com/us/artist/adrian-clark/1453021587",
      "soundcloud": "https://soundcloud.com/adrian-clark-music",
      "facebook": "https://www.facebook.com/artist.adrian.clark",
      "twitter": "",
      "instagram": "https://www.instagram.com/adrian.r.clark/",
      "spotify": "https://open.spotify.com/artist/2f6F5wBEI9NlYNWfGzSIXY",
      "created_at": "2023-01-04T17:18:33.433+11:00",
      "updated_at": "2023-01-04T17:18:33.433+11:00"
    },
    {
      "id": "fb39db77-f753-4c6d-a35a-ce0797eb5f49",
      "name": "The Beez",
      "sort_name": "Beez",
      "summary": "The Beez yodellin', thigh slappin', lederhosen wettin' dance fest of German flavoured music featuring Deta C. Rayner (accordion, vocals) and Rob Rayner (guitar, vocals). Thrill to comic classics from Rammstein to Kraftwerk; tear off that dirndl and shake a Teutonic Tailfeather to Nena's 99 Red Balloons, jive to Germafied Oz Rock Classics from Oils to Icehouse but, most of all, be entertained- that's an order!",
      "image_name": "TheBeez",
      "website": "www.thebeez.de",
      "youtube": "",
      "itunes": "",
      "soundcloud": "",
      "facebook": "www.thebeez.de",
      "twitter": "",
      "instagram": "",
      "spotify": "",
      "created_at": "2023-01-05T11:16:29.932+11:00",
      "updated_at": "2023-01-05T11:16:29.932+11:00"
    },
    {
      "id": "dd35ec5c-6065-4522-9350-f8bfbe260393",
      "name": "Blue Moon Marquee",
      "sort_name": "Blue Moon Marquee",
      "summary": "Blue Moon Marquee perform original compositions influenced by anything that swings, jumps or grooves. Carving a path through blues, jazz, jump jive, folk, country, swing and Indigenous soul, their sound defies categorisation. It stomps and struts through the wilds, conjuring a blend where Howlin’ Wolf tangos with Django, Ernest Tubb shoots firecrackers with Cab Calloway, and Memphis Minnie throws dice with Screamin’ Jay Hawkins. ",
      "image_name": "BlueMoonMarquee",
      "website": "https://bluemoonmarquee.com/",
      "youtube": "https://www.youtube.com/BlueMoonMarquee",
      "itunes": "",
      "soundcloud": "",
      "facebook": "https://www.facebook.com/bluemoonmarquee/",
      "twitter": "",
      "instagram": "https://www.instagram.com/bluemoonmarquee/",
      "spotify": "",
      "created_at": "2023-01-04T17:19:59.823+11:00",
      "updated_at": "2023-01-04T17:19:59.823+11:00"
    },
    {
      "id": "50edbac6-be84-488a-b7c8-22e302ca4e66",
      "name": "Bromham",
      "sort_name": "Bromham",
      "summary": "Bromham are an eclectic, sprawling folk band from Adelaide, Australia that weave their broad range of instruments into one raucous yet harmonious sound. The big band exudes joy with music and stories that celebrate family, community, and equality and a live show that features heartfelt storytelling, soaring group vocals and members roaming the crowd.  This musical community travel to the Yackandanah Folk Festival after overwhelming receptions at both the National and Kangaroo Valley folk festivals in 2022 where people of all ages fell in love with their them",
      "image_name": "Bromham",
      "website": "",
      "youtube": "",
      "itunes": "",
      "soundcloud": "",
      "facebook": "https://www.facebook.com/bromhammusic/",
      "twitter": "",
      "instagram": "",
      "spotify": "https://open.spotify.com/artist/6iSl1lOGjiegFNwjBwK6d5",
      "created_at": "2023-01-04T17:21:53.223+11:00",
      "updated_at": "2023-01-04T17:21:53.223+11:00"
    },
    {
      "id": "26eb0a00-8b56-4d7a-8d7a-3092f1eb32f2",
      "name": "Brydee Rose",
      "sort_name": "Brydee Rose",
      "summary": "We're still waiting on some more details here… we'll update you soon!",
      "image_name": "BrydeeRose",
      "website": "",
      "youtube": "",
      "itunes": "",
      "soundcloud": "",
      "facebook": "https://www.facebook.com/events/588773646246984/?source=3u0026action_history=nullu0026paipv=0u0026eav=AfZ_KiVyJLGn5fGLyMe-fcQ3xdifTeki2RAlZKDKAMQBzjlSbbYsVJwOLPIVNAvHujcu0026_rdr",
      "twitter": "",
      "instagram": "",
      "spotify": "",
      "created_at": "2023-01-04T17:24:17.538+11:00",
      "updated_at": "2023-01-04T17:37:00.263+11:00"
    },
    {
      "id": "3dc0f7bc-6963-4165-9983-721a86d386a8",
      "name": "Candice McLeod",
      "sort_name": "Candice McLeod",
      "summary": "Her live performances have been described as endearing; her 2017 debut album, raw and real. Candice McLeod is a modern-folk songstress, with ten years of road-life up her sleeve. Quickly stitching herself within the fabric of Yackandandah's (VIC) community three years ago, she continues to grow as a soulful weaver of vulnerability and strength through song. ",
      "image_name": "CandiceMcLeod",
      "website": "",
      "youtube": "https://youtu.be/SKXeeIWbgL4",
      "itunes": "",
      "soundcloud": "",
      "facebook": "www.facebook.com/candicemcleodmusic",
      "twitter": "",
      "instagram": "www.instagram.com/candicemcleodmusic ",
      "spotify": "",
      "created_at": "2023-01-04T17:24:58.574+11:00",
      "updated_at": "2023-01-04T17:24:58.574+11:00"
    },
    {
      "id": "e287a74b-0ef7-46e9-8c99-6e82d4953bb6",
      "name": "Cat Canteri",
      "sort_name": "Cat Canteri",
      "summary": "Details coming soon",
      "image_name": "CatCanteri",
      "website": "https://www.catcanteri.com/",
      "youtube": "https://www.youtube.com/watch?v=vVYdNN-BWQE",
      "itunes": "",
      "soundcloud": "",
      "facebook": "https://www.facebook.com/catcanterimusic",
      "twitter": "",
      "instagram": "",
      "spotify": "",
      "created_at": "2023-01-04T17:25:47.093+11:00",
      "updated_at": "2023-01-04T17:25:47.093+11:00"
    },
    {
      "id": "e26d0f55-50e8-4b22-ba92-7aca30289a69",
      "name": "Chris Cavill",
      "sort_name": "Chris Cavill",
      "summary": "In 2021, Chris Cavill released Lionheart; a heart-warming album dedicated to his father following a 28-year battle with Multiple Sclerosis. The album was a huge success, racking up over 100,000 global streams. His most recent release is a cover of Neil Young’s ‘Old Man’, and features his 8-year old son.",
      "image_name": "ChrisCavill",
      "website": "www.chriscavillmusic.com",
      "youtube": "www.youtube.com/chriscavillmusic",
      "itunes": "",
      "soundcloud": "",
      "facebook": "www.facebook.com/chriscavillmusic",
      "twitter": "",
      "instagram": "https://www.instagram.com/chris.cavill/",
      "spotify": "https://open.spotify.com/artist/1C6ndffV7VCL47YkvqrIva",
      "created_at": "2023-01-04T17:27:12.615+11:00",
      "updated_at": "2023-01-04T17:27:12.615+11:00"
    },
    {
      "id": "04954c63-44d7-47c8-97d2-9502342c23f3",
      "name": "Corn Nut Creek",
      "sort_name": "Corn Nut Creek",
      "summary": "Details coming soon",
      "image_name": "CornNutCreek",
      "website": "https://www.cornnutcreek.com/",
      "youtube": "",
      "itunes": "",
      "soundcloud": "",
      "facebook": "https://www.facebook.com/cornnutcreek/",
      "twitter": "https://twitter.com/CreekNut",
      "instagram": "https://www.instagram.com/cornnutcreek/",
      "spotify": "",
      "created_at": "2023-01-04T17:28:56.437+11:00",
      "updated_at": "2023-01-04T17:28:56.437+11:00"
    },
    {
      "id": "681a35a9-58ad-4fc7-bda8-2e96378e5e8c",
      "name": "Dani Larkin",
      "sort_name": "Dani Larkin",
      "summary": "We're still waiting on some more details here… we'll update you soon!",
      "image_name": "DaniLarkin",
      "website": "https://www.danilarkin.com/",
      "youtube": "",
      "itunes": "",
      "soundcloud": "",
      "facebook": "https://www.facebook.com/DaniLarkinmusic",
      "twitter": "https://twitter.com/Dani_Larkin_",
      "instagram": "https://www.instagram.com/dani_larkin_/",
      "spotify": "https://open.spotify.com/artist/6s74lp18Qqs5s46mJKtxWi?nd=1",
      "created_at": "2023-01-04T17:30:49.092+11:00",
      "updated_at": "2023-01-04T17:30:49.092+11:00"
    },
    {
      "id": "52fc5802-bea8-4e52-aa69-e1d293911276",
      "name": "Daniel Champagne",
      "sort_name": "Daniel Champagne",
      "summary": "We're still waiting on some more details here… we'll update you soon!",
      "image_name": "DanielChampagne",
      "website": "https://danielchampagnemusic.com/",
      "youtube": "https://www.youtube.com/user/Champagnemusic1",
      "itunes": "https://music.apple.com/au/artist/daniel-champagne/424584843",
      "soundcloud": "",
      "facebook": "https://www.facebook.com/danielchampagnemusic",
      "twitter": "",
      "instagram": "https://www.instagram.com/danielchampagnemusic/",
      "spotify": "https://open.spotify.com/artist/5VbD0260te11AgTgTs5odC",
      "created_at": "2023-01-04T17:33:25.887+11:00",
      "updated_at": "2023-01-04T17:33:25.887+11:00"
    },
    {
      "id": "4b07b759-e094-4171-9d39-0c47145d442a",
      "name": "Dean Haitani",
      "sort_name": "Dean Haitani",
      "summary": "We're still waiting on some more details here… we'll update you soon!",
      "image_name": "DeanHaitani",
      "website": "https://www.deanhaitanimusic.com/music",
      "youtube": "",
      "itunes": "",
      "soundcloud": "",
      "facebook": "https://www.facebook.com/deanhaitanimusic",
      "twitter": "",
      "instagram": "",
      "spotify": "",
      "created_at": "2023-01-04T17:41:22.071+11:00",
      "updated_at": "2023-01-04T17:41:22.071+11:00"
    },
    {
      "id": "577161f4-4974-4121-8ff5-900744d89d41",
      "name": "Emily Barker",
      "sort_name": "Emily Barker",
      "summary": "Emily Barker is an award-winning singer-songwriter, best known as the writer and performer of the theme to the BBC’s hugely successful crime drama Wallander starring Kenneth Branagh. She has released music as a solo artist as well as with various bands and collaborations including The Red Clay Halo, Frank Turner, Vena Portae, Marry Waterson and Applewood Road (with whom she released a remarkable album of original songs recorded live around a single microphone, dubbed “flawless” by The Sunday Times) and has written for film, including composing the soundtrack for Jake Gavin’s lauded debut feature Hector starring Peter Mullan and Keith Allen",
      "image_name": "EmilyBarker",
      "website": "https://www.emilybarker.com/",
      "youtube": "https://www.youtube.com/emilybarkerhalo",
      "itunes": "",
      "soundcloud": "",
      "facebook": "https://www.facebook.com/EmilyBarkerHalo/",
      "twitter": "https://twitter.com/emilybarkerhalo",
      "instagram": "https://www.instagram.com/emilybarkerhalo/",
      "spotify": "https://open.spotify.com/artist/25uHIpsCWoj8wEHFOEhbuV",
      "created_at": "2023-01-04T17:43:48.345+11:00",
      "updated_at": "2023-01-04T17:43:48.345+11:00"
    },
    {
      "id": "c18a72de-09ae-458a-a61c-a9eca03fbeb3",
      "name": "Floyd Thursby",
      "sort_name": "Floyd Thursby",
      "summary": "Folk singer and songwriter Floyd Thursby has years of songs and stories to share, whether busking in the streets of Iran, playing in nursing homes, or performing for the Prime Minister of Vietnam. ‘To those in flames’ (2019) ALBUM OF THE WEEK: The Age. SHORTLISTED 2021 Music Victoria Awards.",
      "image_name": "FloydThursby",
      "website": "www.floydthursby.com ",
      "youtube": "https://www.youtube.com/watch?v=arQ8pYuhZU4",
      "itunes": "",
      "soundcloud": "",
      "facebook": "http://www.facebook.com/MrFloydThursby",
      "twitter": "",
      "instagram": "",
      "spotify": "",
      "created_at": "2023-01-04T17:45:54.487+11:00",
      "updated_at": "2023-01-04T17:45:54.487+11:00"
    },
    {
      "id": "239a5e2a-c9b8-4a74-9698-db1ced69b86a",
      "name": "Forgotten Land",
      "sort_name": "Forgotten Land",
      "summary": "Gemma and Dave King are a husband and wife duo now happily living in Yackandandah. Originally from Bath in the UK, this is where they began their musical journey. Gem sings from the heart, taking you through their life experiences and events including Gem’s song “Graceful Yackandandah”. Dave accompanies Gem with his funky beats on percussion drums.",
      "image_name": "ForgottenLand",
      "website": "",
      "youtube": "",
      "itunes": "",
      "soundcloud": "",
      "facebook": "",
      "twitter": "",
      "instagram": "",
      "spotify": "",
      "created_at": "2023-01-04T17:46:54.123+11:00",
      "updated_at": "2023-01-04T17:46:54.123+11:00"
    },
    {
      "id": "e82c740f-a874-4bfa-a66d-bdf89de48afc",
      "name": "Fred Smith",
      "sort_name": "Fred Smith",
      "summary": "We're still waiting on some more details here… we'll update you soon!",
      "image_name": "FredSmith",
      "website": "http://www.fredsmith.com.au",
      "youtube": "https://www.youtube.com/playlist?list=PLukE1Y6AbcjgWW4TxRRbOcNO6MhO9-I1C",
      "itunes": "",
      "soundcloud": "",
      "facebook": "https://www.facebook.com/fredsmithmusic/  ",
      "twitter": "",
      "instagram": "",
      "spotify": "",
      "created_at": "2023-01-04T17:47:40.269+11:00",
      "updated_at": "2023-01-04T17:47:40.269+11:00"
    },
    {
      "id": "448fe565-1dca-430c-8e45-7b0d6c1e1e49",
      "name": "Gordon Mullen",
      "sort_name": "Gordon Mullen",
      "summary": "Gordon Mullen delivers a masterclass on the ukulele, weaving intricate pickings through songs by Bruce Cockburn, Muse, Midnight Oil and Nordic classics. Coming off a standing ovation at his previous Festival appearance, Mullen will bookend these artists on keyboard with originals including a call to action on climate change, refugee care and the tender recognition of the outback woman who loses all to drought and disease. Not to be missed. ",
      "image_name": "GordonMullen",
      "website": "",
      "youtube": "",
      "itunes": "",
      "soundcloud": "",
      "facebook": "",
      "twitter": "",
      "instagram": "",
      "spotify": "",
      "created_at": "2023-01-04T17:48:25.488+11:00",
      "updated_at": "2023-01-06T12:09:55.959+11:00"
    },
    {
      "id": "ead1ecf2-09a3-4028-9432-3608efac274a",
      "name": "Great Aunt",
      "sort_name": "Great Aunt",
      "summary": "There's a buzz about Great Aunt - theirs is a joyous and eclectic approach to making music. Together, songwriter/instrumentalists Megan Bird and Chelsea Allen draw inspiration from the traditions of old-time, bluegrass and gospel music, and their diverse backgrounds in punk and jazz, to craft modern musical stories. The duo has delighted audiences at some of Australia’s finest music and arts festivals with tales of joy and grief, whiskey and wine, gratitude and purpose-seeking.",
      "image_name": "GreatAunt",
      "website": "www.greatauntmusic.com",
      "youtube": "",
      "itunes": "",
      "soundcloud": "",
      "facebook": "https://www.facebook.com/greatauntmusic",
      "twitter": "https://twitter.com/greatauntmusic",
      "instagram": "https://www.instagram.com/greatauntmusic/",
      "spotify": "",
      "created_at": "2023-01-04T17:54:05.089+11:00",
      "updated_at": "2023-01-06T12:11:59.508+11:00"
    },
    {
      "id": "d3ec4f72-b8a1-4804-946b-ccdc7699091d",
      "name": "Gretta Ziller",
      "sort_name": "Gretta Ziller",
      "summary": "Gretta Ziller’s sound may bear the hallmarks of classic Americana music but its essence is far more diverse. The Melbourne songstress’ roots span jazz, blues, rock, pop and classical. Gretta’s eclectic musical upbringing, is reflected in the varied tracks of her debut full-length album Queen of Boomtown.",
      "image_name": "GrettaZiller",
      "website": "http://www.grettaziller.com",
      "youtube": "",
      "itunes": "https://music.apple.com/au/artist/gretta-ziller/348673625",
      "soundcloud": "",
      "facebook": "https://www.facebook.com/",
      "twitter": "https://twitter.com/",
      "instagram": "https://www.instagram.com/",
      "spotify": "https://open.spotify.com/artist/0z328yAQPLGxQyGhzXLf98?dl_branch=1u0026nd=1",
      "created_at": "2023-01-04T17:51:04.530+11:00",
      "updated_at": "2023-01-06T12:12:05.974+11:00"
    },
    {
      "id": "61cca078-d1c9-47e4-8bcf-6b61aa712813",
      "name": "Hannah Schmidli",
      "sort_name": "Hannah Schmidli",
      "summary": "Hannah is a dynamic singer-songwriter who displays a writing maturity beyond her 18 years of age. Her performances are engaging and thoroughly entertaining. She has the rare ability to connect with audience members young or old and weaves images with her lyrics, stories and music.",
      "image_name": "HannahSchmidli",
      "website": "hannahschmidli.com",
      "youtube": "https://www.youtube.com/@hannahschmidli",
      "itunes": "",
      "soundcloud": "",
      "facebook": "https://www.facebook.com/hannahschmidlimusic/",
      "twitter": "",
      "instagram": "https://www.instagram.com/hannahschmidlii/",
      "spotify": "",
      "created_at": "2023-01-04T17:56:35.598+11:00",
      "updated_at": "2023-01-04T17:56:35.598+11:00"
    },
    {
      "id": "689e4393-11b4-46b5-a4a2-d832c5b00c5e",
      "name": "Jayda Jean",
      "sort_name": "Jayda Jean",
      "summary": "Jayda Jean is a young singer-songwriter from the Yarra Valley. Her songwriting has emerged from folk beginnings but has taken a modern turn. She is a multi-award winning songwriter, having won two national song writing competitions by the age of 15. Jayda Jean is touring her debut EP “Through Your Eyes” which can be streamed everywhere.",
      "image_name": "JaydaJean",
      "website": "",
      "youtube": "https://www.youtube.com/watch?v=ur0ONlZxrXw",
      "itunes": "",
      "soundcloud": "",
      "facebook": "https://www.facebook.com/jaydajeanmusic",
      "twitter": "",
      "instagram": "",
      "spotify": "",
      "created_at": "2023-01-04T17:59:40.936+11:00",
      "updated_at": "2023-01-06T12:09:50.276+11:00"
    },
    {
      "id": "d97eca99-0ac0-4bcc-ab18-111ae20e5e59",
      "name": "John Smith",
      "sort_name": "John Smith",
      "summary": "With his honey-on-gravel voice and mesmerising fingerstyle guitar, John Smith has built a reputation as one of the UK’s finest guitarists and songwriters. John’s intimate take on love, loss and the journey we make, combined with his innovative guitar work, have won him a loyal following around the globe. “The future of Folk Music” – John Renbourn.",
      "image_name": "JohnSmith",
      "website": "https://www.johnsmithjohnsmith.com/",
      "youtube": "https://www.youtube.com/thejohnsmith",
      "itunes": "",
      "soundcloud": "",
      "facebook": "https://www.facebook.com/thejohnsmith",
      "twitter": "https://twitter.com/thejohnsmith",
      "instagram": "https://www.instagram.com/thejohnsmith/",
      "spotify": "https://open.spotify.com/artist/56GNqAFg9wJNTwcHsJhyS2",
      "created_at": "2023-01-04T18:01:44.374+11:00",
      "updated_at": "2023-01-04T18:01:44.374+11:00"
    },
    {
      "id": "48f73412-53eb-43ca-9a0d-882e790d4f46",
      "name": "Julian James and the Moonshine State",
      "sort_name": "Julian James and the Moonshine State",
      "summary": "We're still waiting on some more details here… we'll update you soon!",
      "image_name": "JulianJames",
      "website": "www.julianjames.com.au",
      "youtube": "https://www.youtube.com/channel/julianjamesartist",
      "itunes": "",
      "soundcloud": "",
      "facebook": "www.facebook.com/julianjamesartist",
      "twitter": "",
      "instagram": "",
      "spotify": "",
      "created_at": "2023-01-05T12:03:32.673+11:00",
      "updated_at": "2023-01-06T12:11:27.853+11:00"
    },
    {
      "id": "290d7f05-a286-413e-bf71-ff798aa32a90",
      "name": "Niamh Regan",
      "sort_name": "Niamh Regan",
      "summary": "Niamh Regan is a critically acclaimed songwriter from county Galway, Ireland. Her debut album Hemet announced her arrival as one of the most distinctive songwriters in Ireland today. Earning nominations for both the RTE Folk Awards’ and the Choice Awards’ Album of the Year.  nRegan honed her craft as a songwriter by travelling between Ireland and California, writing about her experiences along the way. As a result, her songs seamlessly weave the intimacy of the Irish lyrical tradition with the expansive breadth of American songwriters such as Karen Dalton, Stevie Nicks, and Joni Mitchell, but the resulting sound is entirely her own.",
      "image_name": "NiamhRegan",
      "website": "http://niamhregan.com/",
      "youtube": "",
      "itunes": "",
      "soundcloud": "",
      "facebook": "https://www.facebook.com/niamhreganmusic",
      "twitter": "https://twitter.com/niamhreganmusic",
      "instagram": "https://www.instagram.com/niamhreganmusic/",
      "spotify": "",
      "created_at": "2023-01-05T11:09:56.797+11:00",
      "updated_at": "2023-01-05T11:09:56.797+11:00"
    },
    {
      "id": "21192f0c-ba89-49fa-a88e-c0dc10087652",
      "name": "Owen Campbell",
      "sort_name": "Owen Campbell",
      "summary": "Owen Campbell is alternative blues and soulful cosmic rock at its best.nInspired by the tempo of the ocean, Owen’s sound is best described as smouldering guitar work running from bluesy riffs and soulful finger-picking to lap steel guitar solos using a shot glass slide and gritty caramel vocals. ",
      "image_name": "OwenCampbell",
      "website": "",
      "youtube": "",
      "itunes": "",
      "soundcloud": "",
      "facebook": "",
      "twitter": "",
      "instagram": "",
      "spotify": "",
      "created_at": "2023-01-05T11:10:50.609+11:00",
      "updated_at": "2023-01-05T11:10:50.609+11:00"
    },
    {
      "id": "50397840-0c70-4446-bdf6-9c24c2f163a9",
      "name": "Pete Denahy",
      "sort_name": "Pete Denahy",
      "summary": "Pete cut his teeth with the Ploughboys in Melbourne in the mid 90’s and went on to tour as fiddle player and comic with Slim Dusty from 1998 to 2002 as the last musician Slim hired for his Travelling Country Band.nnHis show today is a blend of his comedy, country/bluegrass songs and energetic fiddle playing. He is joined this time by Aron McLean on upright bass and Jeff Mercer on electric guitar. Jeff also toured with Slim and it was on the road that Pete and Jeff became musical brothers. Aron has been gigging with Pete for over ten years. The combination of these three on stage pretty much means “good time had by all”!",
      "image_name": "PeteDenahy",
      "website": "https://www.petedenahy.com/",
      "youtube": "",
      "itunes": "",
      "soundcloud": "",
      "facebook": "https://www.facebook.com/pete.denahy",
      "twitter": "",
      "instagram": "https://www.instagram.com/pete_denahy/",
      "spotify": "",
      "created_at": "2023-01-05T11:12:15.143+11:00",
      "updated_at": "2023-01-05T11:12:15.143+11:00"
    },
    {
      "id": "8deb583b-5209-4901-a392-812fe52bc990",
      "name": "Riflebirds",
      "sort_name": "Riflebirds",
      "summary": "Get ready for electrifying, hip-shakin, vintage rock soul with Melbourne's high-flying Riflebirds. The bands unique guitar and keyboard driven sound - performed with passion and energy - has earned Riflebirds a reputation as one of the finest live acts around. With their fourth and most adventurous album 'Keep It Together' out recently, the band is making its Yackandandah festival debut.",
      "image_name": "Riflebirds",
      "website": "https://www.riflebirds.com.au/",
      "youtube": "https://www.youtube.com/channel/UC_aEwi_sX6nN-AmAtR569-Q",
      "itunes": "https://music.apple.com/au/artist/riflebirds/994762948",
      "soundcloud": "https://soundcloud.com/riflebirds",
      "facebook": "https://www.facebook.com/riflebirdsband",
      "twitter": "",
      "instagram": "https://www.instagram.com/riflebirds/",
      "spotify": "https://open.spotify.com/artist/7bzzkiQIc8GtB1jKqEtqFv",
      "created_at": "2023-01-05T11:14:07.786+11:00",
      "updated_at": "2023-01-05T11:14:07.786+11:00"
    },
    {
      "id": "91cb6c07-16a0-4dc7-bc47-1ee348e18789",
      "name": "Saoirse",
      "sort_name": "Saoirse",
      "summary": "A Saoirse performance will delight the audience with a little bit of everything Celtic, from heartfelt ballads, original songs and stories, to lively jigs and reels, with even an Irish step dance or two! With excellent musicianship and harmonies that will take your breath away, a concert promises to entertain; to warm hearts, and leave toes tapping for more!",
      "image_name": "Saoirse",
      "website": "http://www.saoirse.com.au/",
      "youtube": "",
      "itunes": "",
      "soundcloud": "",
      "facebook": "https://www.facebook.com/saoirsemelbourne",
      "twitter": "",
      "instagram": "",
      "spotify": "",
      "created_at": "2023-01-05T11:15:03.267+11:00",
      "updated_at": "2023-01-05T11:15:03.267+11:00"
    },
    {
      "id": "c7448b2e-8690-42cb-b533-cd085abb135c",
      "name": "The Burning Hell",
      "sort_name": "The Burning Hell",
      "summary": "The Burning Hell is the ongoing musical project of songwriter Mathias Kom (guitar) and Ariel Sharratt (saxophone, bass, drums), based in Prince Edward Island, Canada, and joined for their Australian tour in 2023 by Maria Peddle from Newfoundland (violin, saxophone, keys, bass, drums). Their densely populated genre-shifting songs are packed with an abundance of literary, historical, cultural, and pop-cultural forebears, stories and hooks. They move with heavy rhyme and a light step, incorporating a frequent fixation on apocalypse and ruin into work that celebrates participation in a surprising and even occasionally beautiful world. Which is to say they’re good dance partners and they want to dance with you",
      "image_name": "TheBurningHell",
      "website": "https://www.wearetheburninghell.com/",
      "youtube": "https://www.youtube.com/user/burninghellofficial",
      "itunes": null,
      "soundcloud": null,
      "facebook": "https://www.facebook.com/theburninghell",
      "twitter": null,
      "instagram": null,
      "spotify": null,
      "created_at": "2023-01-05T12:03:32.676+11:00",
      "updated_at": "2023-01-05T12:03:32.676+11:00"
    },
    {
      "id": "0dad927b-9eb7-4854-a505-c23499b01db3",
      "name": "The Go Set",
      "sort_name": "The Go Set",
      "summary": "Twenty years down the line and The Go Set still sound as fierce, as vital, as the first day they set foot on a stage. The Geelong-based band has always squeezed out the sparks from the place where rock’n’roll collides with the spirit of Celtic folk. I have Irish and Scottish heritage through my grandparents on both sides and that was the kind of music I heard at home,” Keenan says. “As a little kid I listened to those traditional songs with my nan on an old record player. Then when I was discovering bands and heard The Pogues, it all made sense.” The ghosts of those who have come before are never too far away in the songs of The Go Set, and the album’s title tune is one of their finest on the topic. Dust off the dancing shoes and be ready.",
      "image_name": "TheGoSet",
      "website": "https://www.thegoset.com/",
      "youtube": "https://www.youtube.com/user/thegoset",
      "itunes": null,
      "soundcloud": null,
      "facebook": "https://www.facebook.com/thegoset",
      "twitter": null,
      "instagram": null,
      "spotify": null,
      "created_at": "2023-01-05T12:03:32.678+11:00",
      "updated_at": "2023-01-05T12:03:32.678+11:00"
    },
    {
      "id": "c85b45d8-6675-497a-a987-1d0e42e298a4",
      "name": "The Humbuckin' Pickups",
      "sort_name": "The Humbuckin' Pickups",
      "summary": "We're still waiting on some more details here… we'll update you soon!",
      "image_name": "TheHumbuckinPickups",
      "website": "www.thehumbuckinpickups.com.au",
      "youtube": "https://www.youtube.com/watch?v=i9ik3ZWbyt8",
      "itunes": null,
      "soundcloud": null,
      "facebook": "www.facebook.com/TheHumbuckinPickups",
      "twitter": null,
      "instagram": null,
      "spotify": null,
      "created_at": "2023-01-05T12:03:32.679+11:00",
      "updated_at": "2023-01-05T12:03:32.679+11:00"
    },
    {
      "id": "b7bfe928-9e15-4f7f-8dfe-f77daed6a419",
      "name": "The Maes",
      "sort_name": "The Maes",
      "summary": "The Maes (sisters Maggie u0026 Elsie Rigby) grew up the children of folk musicians, immersed in folk festivals, choir rehearsals and campfire sessions. Since 2014, they’ve been touring full time, playing some of the world’s most prestigious roots music festivals, including the Telluride Bluegrass Festival and Edmonton Folk Festival. “Quite simply breathtaking” – Rhythms Magazine.",
      "image_name": "TheMaes",
      "website": "https://themaes.com.au",
      "youtube": "https://www.youtube.com/watch?v=uz0skPGKI5U",
      "itunes": null,
      "soundcloud": null,
      "facebook": "https://www.facebook.com/themaesband",
      "twitter": null,
      "instagram": null,
      "spotify": null,
      "created_at": "2023-01-05T12:03:32.681+11:00",
      "updated_at": "2023-01-05T12:03:32.681+11:00"
    },
    {
      "id": "f1af8bf0-966d-483c-88db-abf1f0736aab",
      "name": "The Pigs",
      "sort_name": "The Pigs",
      "summary": "The family that plays together, stays together... and in the nutty world of The Pigs, family (and beer, and bluegrass) is all that matters... and did I mention… you’re family too. In these troubling times you can count on The Pigs... They have not blurred their backgrounds, stockpiled dunny paper or learned anything remotely.T-Bone, Stretch, Cousin Shamus, Cousin Bert u0026 Cousin Montz last name PIG, like to have fun and their music speaks to that… but also pokes much deeper... life, love, heartache, Robot Goats even. Expect to be shocked by their dress u0026 hear their many hits – even that one about Moisturiser. ",
      "image_name": "ThePigs",
      "website": "https://thepigs.com.au/",
      "youtube": "https://www.youtube.com/watch?v=0ncgv2HE5Ns",
      "itunes": null,
      "soundcloud": null,
      "facebook": "https://www.facebook.com/thepigsofficial",
      "twitter": null,
      "instagram": null,
      "spotify": null,
      "created_at": "2023-01-05T12:03:32.682+11:00",
      "updated_at": "2023-01-05T12:03:32.682+11:00"
    },
    {
      "id": "55268404-415a-4fd9-a0d4-96a418b6c83d",
      "name": "The Ploughboys",
      "sort_name": "The Ploughboys",
      "summary": "We're still waiting on some more details here… we'll update you soon!",
      "image_name": "ThePloughboys",
      "website": "https://www.facebook.com/ploughboysaustralia",
      "youtube": "https://www.youtube.com/watch?v=rUU8zqcG160",
      "itunes": null,
      "soundcloud": null,
      "facebook": "https://www.facebook.com/ploughboysaustralia",
      "twitter": null,
      "instagram": null,
      "spotify": null,
      "created_at": "2023-01-05T12:03:32.684+11:00",
      "updated_at": "2023-01-05T12:03:32.684+11:00"
    },
    {
      "id": "8e8df656-79af-4d43-a3e7-ba05a56354e1",
      "name": "The Royal High Jinx",
      "sort_name": "The Royal High Jinx",
      "summary": "Melbourne's mesmerising contemporary world music band The Royal High Jinx burst onto Australian festival stages with originality, virtuosity u0026 theatricality. Their songs u0026 tunes are inspired by European traditions, peppered with Gypsy Jazz, Latin Balkan u0026 Swing grooves with a pinch of Folk Cabaret. Described as the “Balkan Abba” for their catchy songs u0026 glamorous show, enjoy their musical celebration.",
      "image_name": "TheRoyalHighJinx",
      "website": "http://www.theroyalhighjinx.com",
      "youtube": "https://bit.ly/2HSyGmC",
      "itunes": null,
      "soundcloud": null,
      "facebook": "https://www.facebook.com/ theroyalhighjinxband/",
      "twitter": null,
      "instagram": null,
      "spotify": null,
      "created_at": "2023-01-05T12:03:32.685+11:00",
      "updated_at": "2023-01-05T12:03:32.685+11:00"
    },
    {
      "id": "c0aed526-668b-4f45-8fd5-c72a4a727e45",
      "name": "The Weeping Willows",
      "sort_name": "The Weeping Willows",
      "summary": "CMAA ‘Golden Guitar’, Australian Folk Music and Music Victoria award winners, The Weeping Willows (Laura Coates and Andrew Wrigglesworth) are a couple of old souls, steeped in Bluegrass tradition and draped in Gothic Americana imagery.  They regale their audiences with stories of sunshine and romance, God and The Devil, murder and decay.  That kind of description might make them sound like some carefully contrived concept-act but there’s something truly different about The Weeping Willows: they really mean it...",
      "image_name": "TheWeepingWillows",
      "website": "http://www.theweepingwillows.com.au",
      "youtube": "https://www.youtube.com/watch?v=P1oMwFyOBjk",
      "itunes": null,
      "soundcloud": null,
      "facebook": "https://www.facebook.com/theweepingwillows",
      "twitter": null,
      "instagram": null,
      "spotify": null,
      "created_at": "2023-01-05T12:03:32.686+11:00",
      "updated_at": "2023-01-05T12:03:32.686+11:00"
    },
    {
      "id": "3147f515-81b9-4054-a62a-4f9e5b4c4e22",
      "name": "Tim McMillan and Rachel Snow",
      "sort_name": "Tim McMillan and Rachel Snow",
      "summary": "We're still waiting on some more details here… we'll update you soon!",
      "image_name": "TimMcMillan",
      "website": "www.timmcmillanrachelsnow.com",
      "youtube": "https://www.youtube.com/watch?v=ZJDq4c5RA3s",
      "itunes": "",
      "soundcloud": "",
      "facebook": "www.facebook.com/timmcmillan",
      "twitter": "",
      "instagram": "",
      "spotify": "",
      "created_at": "2023-01-05T12:03:32.689+11:00",
      "updated_at": "2023-01-06T12:11:45.355+11:00"
    },
    {
      "id": "0e0421d5-f00e-4c31-b3a4-716fd02ba8fc",
      "name": "Tinman",
      "sort_name": "Tinman",
      "summary": "We're still waiting on some more details here… we'll update you soon!",
      "image_name": "Tinman",
      "website": "https://linktr.ee/Tinmanband",
      "youtube": "https://www.youtube.com/channel/UCTLUf2SE_cyZcI4Pf_qCBlA/videos",
      "itunes": null,
      "soundcloud": null,
      "facebook": "https://www.facebook.com/musicoftinman/",
      "twitter": null,
      "instagram": null,
      "spotify": null,
      "created_at": "2023-01-05T12:03:32.690+11:00",
      "updated_at": "2023-01-05T12:03:32.690+11:00"
    },
    {
      "id": "6d188281-56a7-48c4-b9de-8c2d2b2d5e98",
      "name": "Tom Richardson",
      "sort_name": "Tom Richardson",
      "summary": "We're still waiting on some more details here… we'll update you soon!",
      "image_name": "TomRichardson",
      "website": null,
      "youtube": null,
      "itunes": null,
      "soundcloud": null,
      "facebook": null,
      "twitter": null,
      "instagram": null,
      "spotify": null,
      "created_at": "2023-01-05T12:03:32.692+11:00",
      "updated_at": "2023-01-05T12:03:32.692+11:00"
    },
    {
      "id": "66a1a813-330c-4e77-ba35-e28ba40eee64",
      "name": "Tony McManus",
      "sort_name": "Tony McManus",
      "summary": "Livewire violinist Alana Hunt shreds through furious csardases, Hungarian restaurant serenades and Transylvanian village folklore chased by Kirri Bachler (double bass), and Sofia Chapman (accordion).Vardos have roamed extensively through Eastern Europe learning from Rroma (Gypsy) musicians, released 6 albums, toured Australia and internationally and appeared in film and television.",
      "image_name": "TonyMcManus",
      "website": "https://www.tonymcmanus.com/     https://www.firsttimesinceaugust.com/",
      "youtube": "https://www.youtube.com/watch?v=upTwC4oEbA0",
      "itunes": null,
      "soundcloud": null,
      "facebook": "https://www.facebook.com/TonyMcManusMusic",
      "twitter": null,
      "instagram": null,
      "spotify": null,
      "created_at": "2023-01-05T12:03:32.693+11:00",
      "updated_at": "2023-01-05T12:03:32.693+11:00"
    },
    {
      "id": "e9f6c941-fee7-4766-9c61-8f9f4870baf8",
      "name": "Vardos",
      "sort_name": "Vardos",
      "summary": "We're still waiting on some more details here… we'll update you soon!",
      "image_name": "Vardos",
      "website": "https://vardos.com.au/",
      "youtube": "https://www.youtube.com/watch?v=W3YaVL5Iflg",
      "itunes": null,
      "soundcloud": null,
      "facebook": "https://www.facebook.com/vardos",
      "twitter": null,
      "instagram": null,
      "spotify": null,
      "created_at": "2023-01-05T12:03:32.694+11:00",
      "updated_at": "2023-01-05T12:03:32.694+11:00"
    },
    {
      "id": "4a2f2eeb-10b6-4656-9bb0-10aab1141a07",
      "name": "While and Matthews",
      "sort_name": "While and Matthews",
      "summary": "The Guardian",
      "image_name": "WhileandMatthews",
      "website": "https://www.whileandmatthews.com/",
      "youtube": "https://www.youtube.com/watch?v=zmo_bNTUqAM",
      "itunes": null,
      "soundcloud": null,
      "facebook": "https://www.facebook.com/whileandmatthews/",
      "twitter": null,
      "instagram": null,
      "spotify": null,
      "created_at": "2023-01-05T12:03:32.696+11:00",
      "updated_at": "2023-01-05T12:03:32.696+11:00"
    },
    {
      "id": "fbb41fc4-dccf-4364-8281-bae84223965f",
      "name": "Widows of the Parish",
      "sort_name": "Widows of the Parish",
      "summary": "Soul wrenching harmonies, incredible arrangements and great energy. The Widows’ sound is an intoxicating mix of bluegrass, Americana, gospel, and blues. Their gigs include fresh arrangements of both obscure gems and standards from different eras. Gorgeous harmonies from these talented female vocalists will have you alternately stomping your feet or crooning along with them",
      "image_name": "WidowsoftheParish",
      "website": "www.widowsoftheparish.com",
      "youtube": "https://www.youtube.com/channel/UCTDrvd6ZiCTgDwmcIsrrO9A",
      "itunes": null,
      "soundcloud": null,
      "facebook": "https://www.facebook.com/widowsoftheparish",
      "twitter": null,
      "instagram": null,
      "spotify": null,
      "created_at": "2023-01-05T12:03:32.697+11:00",
      "updated_at": "2023-01-05T12:03:32.697+11:00"
    }
  ]
}
